MovingBot_XKMR/MoveBot.py
MovingBot_XKMR/__init__.py
MovingBot-0.0.1.dist-info/LICENSE
MovingBot-0.0.1.dist-info/METADATA
MovingBot-0.0.1.dist-info/WHEEL
MovingBot-0.0.1.dist-info/top_level.txt
MovingBot-0.0.1.dist-info/RECORD
