Metadata-Version: 2.1
Name: MovingBot
Version: 0.0.1
Summary: a script for simulating a object with a direction that can move in said direction
Author-email: XKMR <author@example.com>
Project-URL: Homepage, https://github.com/XKMR/PythonMovingBot
Project-URL: Bug Tracker, https://github.com/XKMR/PythonMovingBot/issues
Classifier: Programming Language :: Python :: 3
Classifier: License :: OSI Approved :: Apache Software License
Classifier: Operating System :: OS Independent
Requires-Python: >3
License-File: LICENSE
